adafruit_max31855.py
adafruit_circuitpython_max31855-3.2.26.dist-info/licenses/LICENSE
adafruit_circuitpython_max31855-3.2.26.dist-info/METADATA
adafruit_circuitpython_max31855-3.2.26.dist-info/WHEEL
adafruit_circuitpython_max31855-3.2.26.dist-info/top_level.txt
adafruit_circuitpython_max31855-3.2.26.dist-info/RECORD
